JciHitachi/__init__.py
JciHitachi/api.py
JciHitachi/aws_connection.py
JciHitachi/connection.py
JciHitachi/model.py
JciHitachi/mqtt_connection.py
JciHitachi/status.py
JciHitachi/utility.py
JciHitachi/cert/AmazonRootCA1.pem
JciHitachi/cert/api-jci-hitachi-smarthome-com-chain.pem
JciHitachi/cert/mqtt-jci-hitachi-smarthome-com-chain.pem
libjcihitachi-1.7.2.dist-info/licenses/LICENSE
libjcihitachi-1.7.2.dist-info/METADATA
libjcihitachi-1.7.2.dist-info/WHEEL
libjcihitachi-1.7.2.dist-info/top_level.txt
libjcihitachi-1.7.2.dist-info/RECORD
