Metadata-Version: 2.4
Name: LibJciHitachi
Version: 1.7.2
Summary: A library for controlling Jci Hitachi devices.
Home-page: https://github.com/qqaatw/LibJciHitachi
Author: Allan Lin
Author-email: qqaatw@gmail.com
Project-URL: Issue Tracker, https://github.com/qqaatw/LibJciHitachi/issues
Project-URL: Documentation, https://libjcihitachi.readthedocs.io/en/latest/
Classifier: Programming Language :: Python :: 3.10
Classifier: Programming Language :: Python :: 3.11
Classifier: Programming Language :: Python :: 3.12
Classifier: Programming Language :: Python :: 3.13
Classifier: License :: OSI Approved :: Apache Software License
Classifier: Operating System :: OS Independent
Requires-Python: >=3.10
License-File: LICENSE
Requires-Dist: awsiotsdk>=1.22.0
Requires-Dist: httpx>=0.28.0
Requires-Dist: paho-mqtt>=2.0.0
Requires-Dist: setuptools
Dynamic: author
Dynamic: author-email
Dynamic: classifier
Dynamic: description
Dynamic: description-content-type
Dynamic: home-page
Dynamic: license-file
Dynamic: project-url
Dynamic: requires-dist
Dynamic: requires-python
Dynamic: summary
